{
    "dominio": "Hidrografia",
    "subdominio": "NASCENTES E CURSOS DE ÁGUA",
    "familia": "RIOS",
    "objeto": "EIXO DO RIO NÃO NAVEGÁVEL NEM FLUTUÁVEL",
    "map": [
        {
            "table": "curso_de_agua_eixo",
            "fields": [
                {
                    "src": "1_geom",
                    "dst": "geometria",
                    "op": "eq"
                },
                {
                    "src": "",
                    "dst": "inicio_objeto",
                    "op": "dnow"
                },
                {
                    "src": "",
                    "dst": "delimitacao_conhecida",
                    "op": "set",
                    "value": "false"
                },
                {
                    "src": "",
                    "dst": "ficticio",
                    "op": "set",
                    "value": "false"
                },
                {
                    "src": "",
                    "dst": "valor_curso_de_agua",
                    "op": "set",
                    "value": "7"
                },
                {
                    "src": "",
                    "dst": "valor_posicao_vertical",
                    "op": "set",
                    "value": "0"
                }
            ]
        }
    ]
}
